tipologias/__init__.py
tipologias/core/__init__.py
tipologias/core/base.py
tipologias/core/participante_pregao.py
tipologias/core/socios_comum.py
tipologias/queries/__init__.py
tipologias/queries/pregao.py
tipologias/queries/socios.py
tipologias/utils/__init__.py
tipologias/utils/asynchronous.py
tipologias/utils/padastools.py
tipologias-0.0.2.dist-info/LICENSE
tipologias-0.0.2.dist-info/METADATA
tipologias-0.0.2.dist-info/WHEEL
tipologias-0.0.2.dist-info/top_level.txt
tipologias-0.0.2.dist-info/RECORD
