Metadata-Version: 2.1
Name: tipologias
Version: 0.0.2
Summary: Pacote de tipologias para trilhas de auditoria do TCMRIO
Author-email: Marciel Barcellos <marciel.barcellos@tcmrio.tc.br>, Nicolau Rodrigues <nicolau.rodrigues@tcmrio.tc.br>
Project-URL: source, https://gitlab.com/tcmrj/tipologias
Project-URL: Bug Tracker, https://gitlab.com/tcmrj/tipologias/-/issues
Classifier: Programming Language :: Python :: 3
Classifier: License :: OSI Approved :: MIT License
Classifier: Operating System :: OS Independent
Requires-Python: >=3.7
License-File: LICENSE
Requires-Dist: pandas (==1.5.3)
Requires-Dist: openpyxl (==3.1.2)
Provides-Extra: tests
Requires-Dist: anyio (==3.6.2) ; extra == 'tests'
Requires-Dist: black (==23.3.0) ; extra == 'tests'
Requires-Dist: cryptography (==37.0.4) ; extra == 'tests'
Requires-Dist: isort (==5.12.0) ; extra == 'tests'
Requires-Dist: pyodbc (==4.0.32) ; extra == 'tests'
Requires-Dist: pytest (==7.3.1) ; extra == 'tests'
Requires-Dist: python-decouple (==3.6) ; extra == 'tests'
Requires-Dist: SQLAlchemy (==1.4.32) ; extra == 'tests'
